mcp_sqlalchemy/__init__.py
mcp_sqlalchemy/__main__.py
mcp_sqlalchemy/_dev.py
mcp_sqlalchemy/server.py
mcp_sqlalchemy-0.2.4.dist-info/licenses/LICENSE
mcp_sqlalchemy-0.2.4.dist-info/METADATA
mcp_sqlalchemy-0.2.4.dist-info/WHEEL
mcp_sqlalchemy-0.2.4.dist-info/entry_points.txt
mcp_sqlalchemy-0.2.4.dist-info/top_level.txt
mcp_sqlalchemy-0.2.4.dist-info/RECORD
