Metadata-Version: 2.4
Name: mcp-sqlalchemy
Version: 0.2.4
Summary: MCP server for SQLAlchemy database interactions - supports SQLite, PostgreSQL, and MySQL
Author-email: Tomer Gabay <tomer.gabay@woonstadrotterdam.nl>, Ben Verhees <ben.verhees@woonstadrotterdam.nl>
License-Expression: MIT
Keywords: mcp,sqlalchemy,database,postgresql,mysql,sqlite
Classifier: Intended Audience :: Developers
Classifier: Programming Language :: Python :: 3
Classifier: Programming Language :: Python :: 3.10
Classifier: Programming Language :: Python :: 3.11
Classifier: Programming Language :: Python :: 3.12
Classifier: Programming Language :: Python :: 3.13
Requires-Python: >=3.10
License-File: LICENSE
Requires-Dist: aiosqlite==0.21.0
Requires-Dist: greenlet==3.2.3
Requires-Dist: mcp[cli]==1.13.1
Requires-Dist: sqlalchemy==2.0.42
Requires-Dist: python-dotenv==1.1.1
Provides-Extra: postgresql
Requires-Dist: asyncpg==0.30.0; extra == "postgresql"
Provides-Extra: mysql
Requires-Dist: aiomysql==0.2.0; extra == "mysql"
Provides-Extra: all
Requires-Dist: mcp-sqlalchemy[postgresql]; extra == "all"
Requires-Dist: mcp-sqlalchemy[mysql]; extra == "all"
Dynamic: license-file
